{
    "metadata": [
        {
            "label": "Titel",
            "value": "Portret van Rector Magnificus prof. J.M. Tienstra door W.G. Hofker"
        },
        {
            "label": "Objectnaam",
            "value": "schilderij"
        },
        {
            "label": "Inventarisnummer",
            "value": "2002.0009.CVB"
        },
        {
            "label": "Datering",
            "value": "1952"
        },
        {
            "label": "Maker",
            "value": "Hofker, Willem Gerard  (maker)"
        },
        {
            "label": "Afmetingen",
            "value": "875,0 (h)  * 770,0 (b)  * 72,0 (d) "
        },
        {
            "label": "Materiaal",
            "value": "olieverf, linnen, hout"
        },
        {
            "label": "Beschrijving",
            "value": "Geschilderd portret van Rector Magnificus prof. Jacob Menno Tienstra, hoogleraar landmeten, waterpassen en geodesie van 1935 tot 1951. Geschilderd door Willem Gerard Hofker."
        },
        {
            "label": "Voorstelling",
            "value": "Tienstra, J.M."
        }
    ],
    "@type": "sc:Manifest",
    "structures": [
        {
            "canvases": ["https://dlc.services/iiif-img/7/18/d1ab2643-cefc-4118-95cf-9f0140950b7c/canvas/c0"],
            "within": "https://dlc.services/iiif-manifest/7/18/3ddd99d2-3b93-49e2-a2d9-97686daf840f/range/range-0.json",
            "@type": "sc:Range",
            "@id": "https://dlc.services/iiif-manifest/7/18/3ddd99d2-3b93-49e2-a2d9-97686daf840f/range/range-0-0.json",
            "label": "0"
        },
        {
            "canvases": ["https://dlc.services/iiif-img/7/18/6db02272-8b64-410c-9d43-c8e69dc1dcd7/canvas/c0"],
            "within": "https://dlc.services/iiif-manifest/7/18/3ddd99d2-3b93-49e2-a2d9-97686daf840f/range/range-0.json",
            "@type": "sc:Range",
            "@id": "https://dlc.services/iiif-manifest/7/18/3ddd99d2-3b93-49e2-a2d9-97686daf840f/range/range-0-1.json",
            "label": "1"
        },
        {
            "canvases": ["https://dlc.services/iiif-img/7/18/ef8f2dd0-73c7-40d3-8930-da4aa56f8eda/canvas/c0"],
            "within": "https://dlc.services/iiif-manifest/7/18/3ddd99d2-3b93-49e2-a2d9-97686daf840f/range/range-0.json",
            "@type": "sc:Range",
            "@id": "https://dlc.services/iiif-manifest/7/18/3ddd99d2-3b93-49e2-a2d9-97686daf840f/range/range-0-2.json",
            "label": "2"
        }
    ],
    "@id": "https://raw.githubusercontent.com/digirati-co-uk/delft-static-site-generator/test/content/objects/3ddd99d2-3b93-49e2-a2d9-97686daf840f.json",
    "sequences": [{
        "viewingDirection": "left-to-right",
        "viewingHint": "paged",
        "canvases": [
            {
                "images": [{
                    "resource": {
                        "@type": "dctypes:Image",
                        "service": {
                            "protocol": "http://iiif.io/api/image",
                            "profile": "http://iiif.io/api/image/2/level1.json",
                            "width": 1228,
                            "@id": "https://dlc.services/iiif-img/7/18/d1ab2643-cefc-4118-95cf-9f0140950b7c",
                            "height": 1818
                        },
                        "width": 1228,
                        "@id": "https://dlc.services/iiif-img/7/18/d1ab2643-cefc-4118-95cf-9f0140950b7c/full/692,1024/0/default.jpg",
                        "height": 1818
                    },
                    "@type": "oa:Annotation",
                    "motivation": "sc:painting",
                    "@id": "https://dlc.services/iiif-img/7/18/d1ab2643-cefc-4118-95cf-9f0140950b7c/imageanno/0",
                    "on": "https://dlc.services/iiif-img/7/18/d1ab2643-cefc-4118-95cf-9f0140950b7c/canvas/c0"
                }],
                "thumbnail": {
                    "@type": "dctypes:Image",
                    "service": {
                        "sizes": [
                            {
                                "width": 692,
                                "height": 1024
                            },
                            {
                                "width": 270,
                                "height": 400
                            },
                            {
                                "width": 135,
                                "height": 200
                            },
                            {
                                "width": 68,
                                "height": 100
                            }
                        ],
                        "profile": [
                            "http://iiif.io/api/image/2/level0.json",
                            {
                                "formats": ["jpg"],
                                "qualities": ["color"],
                                "supports": ["sizeByWhListed"]
                            }
                        ],
                        "width": 692,
                        "@id": "https://dlc.services/thumbs/7/18/d1ab2643-cefc-4118-95cf-9f0140950b7c",
                        "@context": "http://iiif.io/api/image/2/context.json",
                        "height": 1024
                    },
                    "@id": "https://dlc.services/thumbs/7/18/d1ab2643-cefc-4118-95cf-9f0140950b7c/full/full/0/default.jpg"
                },
                "@type": "sc:Canvas",
                "width": 1228,
                "@id": "https://dlc.services/iiif-img/7/18/d1ab2643-cefc-4118-95cf-9f0140950b7c/canvas/c0",
                "label": "Image",
                "height": 1818
            },
            {
                "images": [{
                    "resource": {
                        "@type": "dctypes:Image",
                        "service": {
                            "protocol": "http://iiif.io/api/image",
                            "profile": "http://iiif.io/api/image/2/level1.json",
                            "width": 1228,
                            "@id": "https://dlc.services/iiif-img/7/18/6db02272-8b64-410c-9d43-c8e69dc1dcd7",
                            "height": 1818
                        },
                        "width": 1228,
                        "@id": "https://dlc.services/iiif-img/7/18/6db02272-8b64-410c-9d43-c8e69dc1dcd7/full/692,1024/0/default.jpg",
                        "height": 1818
                    },
                    "@type": "oa:Annotation",
                    "motivation": "sc:painting",
                    "@id": "https://dlc.services/iiif-img/7/18/6db02272-8b64-410c-9d43-c8e69dc1dcd7/imageanno/0",
                    "on": "https://dlc.services/iiif-img/7/18/6db02272-8b64-410c-9d43-c8e69dc1dcd7/canvas/c0"
                }],
                "thumbnail": {
                    "@type": "dctypes:Image",
                    "service": {
                        "sizes": [
                            {
                                "width": 692,
                                "height": 1024
                            },
                            {
                                "width": 270,
                                "height": 400
                            },
                            {
                                "width": 135,
                                "height": 200
                            },
                            {
                                "width": 68,
                                "height": 100
                            }
                        ],
                        "profile": [
                            "http://iiif.io/api/image/2/level0.json",
                            {
                                "formats": ["jpg"],
                                "qualities": ["color"],
                                "supports": ["sizeByWhListed"]
                            }
                        ],
                        "width": 692,
                        "@id": "https://dlc.services/thumbs/7/18/6db02272-8b64-410c-9d43-c8e69dc1dcd7",
                        "@context": "http://iiif.io/api/image/2/context.json",
                        "height": 1024
                    },
                    "@id": "https://dlc.services/thumbs/7/18/6db02272-8b64-410c-9d43-c8e69dc1dcd7/full/full/0/default.jpg"
                },
                "@type": "sc:Canvas",
                "width": 1228,
                "@id": "https://dlc.services/iiif-img/7/18/6db02272-8b64-410c-9d43-c8e69dc1dcd7/canvas/c0",
                "label": "Image",
                "height": 1818
            },
            {
                "images": [{
                    "resource": {
                        "@type": "dctypes:Image",
                        "service": {
                            "protocol": "http://iiif.io/api/image",
                            "profile": "http://iiif.io/api/image/2/level1.json",
                            "width": 3913,
                            "@id": "https://dlc.services/iiif-img/7/18/ef8f2dd0-73c7-40d3-8930-da4aa56f8eda",
                            "height": 4373
                        },
                        "width": 3913,
                        "@id": "https://dlc.services/iiif-img/7/18/ef8f2dd0-73c7-40d3-8930-da4aa56f8eda/full/916,1024/0/default.jpg",
                        "height": 4373
                    },
                    "@type": "oa:Annotation",
                    "motivation": "sc:painting",
                    "@id": "https://dlc.services/iiif-img/7/18/ef8f2dd0-73c7-40d3-8930-da4aa56f8eda/imageanno/0",
                    "on": "https://dlc.services/iiif-img/7/18/ef8f2dd0-73c7-40d3-8930-da4aa56f8eda/canvas/c0"
                }],
                "thumbnail": {
                    "@type": "dctypes:Image",
                    "service": {
                        "sizes": [
                            {
                                "width": 916,
                                "height": 1024
                            },
                            {
                                "width": 358,
                                "height": 400
                            },
                            {
                                "width": 179,
                                "height": 200
                            },
                            {
                                "width": 89,
                                "height": 100
                            }
                        ],
                        "profile": [
                            "http://iiif.io/api/image/2/level0.json",
                            {
                                "formats": ["jpg"],
                                "qualities": ["color"],
                                "supports": ["sizeByWhListed"]
                            }
                        ],
                        "width": 916,
                        "@id": "https://dlc.services/thumbs/7/18/ef8f2dd0-73c7-40d3-8930-da4aa56f8eda",
                        "@context": "http://iiif.io/api/image/2/context.json",
                        "height": 1024
                    },
                    "@id": "https://dlc.services/thumbs/7/18/ef8f2dd0-73c7-40d3-8930-da4aa56f8eda/full/full/0/default.jpg"
                },
                "@type": "sc:Canvas",
                "width": 3913,
                "@id": "https://dlc.services/iiif-img/7/18/ef8f2dd0-73c7-40d3-8930-da4aa56f8eda/canvas/c0",
                "label": "Image",
                "height": 4373
            }
        ],
        "@type": "sc:Sequence",
        "@id": "https://dlc.services/7/18/3ddd99d2-3b93-49e2-a2d9-97686daf840f/sequences/normal",
        "label": "Current page order"
    }],
    "@context": "http://iiif.io/api/presentation/2/context.json"
}